HginitZhongwenWendang/README.md
HginitZhongwenWendang/__init__.py
HginitZhongwenWendang/__main__.py
HginitZhongwenWendang/file.epub
HginitZhongwenWendang/index.html
HginitZhongwenWendang/css/__init__.py
HginitZhongwenWendang/css/annotations.css
HginitZhongwenWendang/css/main.css
HginitZhongwenWendang/css/normalize.css
HginitZhongwenWendang/css/popup.css
HginitZhongwenWendang/font/__init__.py
HginitZhongwenWendang/font/fontello.eot
HginitZhongwenWendang/font/fontello.svg
HginitZhongwenWendang/font/fontello.ttf
HginitZhongwenWendang/font/fontello.woff
HginitZhongwenWendang/img/__init__.py
HginitZhongwenWendang/img/annotator-glyph-sprite.png
HginitZhongwenWendang/img/annotator-icon-sprite.png
HginitZhongwenWendang/img/apple-touch-icon.png
HginitZhongwenWendang/img/cancelfullscreen.png
HginitZhongwenWendang/img/close.png
HginitZhongwenWendang/img/fullscreen.png
HginitZhongwenWendang/img/loader.gif
HginitZhongwenWendang/img/menu-icon.png
HginitZhongwenWendang/img/save.png
HginitZhongwenWendang/img/saved.png
HginitZhongwenWendang/img/settings-s.png
HginitZhongwenWendang/img/settings.png
HginitZhongwenWendang/img/star.png
HginitZhongwenWendang/js/__init__.py
HginitZhongwenWendang/js/epub.js
HginitZhongwenWendang/js/epub.min.js
HginitZhongwenWendang/js/epub.min.map
HginitZhongwenWendang/js/hooks.min.js
HginitZhongwenWendang/js/hooks.min.map
HginitZhongwenWendang/js/reader.js
HginitZhongwenWendang/js/reader.js.map
HginitZhongwenWendang/js/reader.min.js
HginitZhongwenWendang/js/reader.min.map
HginitZhongwenWendang/js/hooks/__init__.py
HginitZhongwenWendang/js/hooks/extensions/__init__.py
HginitZhongwenWendang/js/hooks/extensions/highlight.js
HginitZhongwenWendang/js/libs/__init__.py
HginitZhongwenWendang/js/libs/jquery.min.js
HginitZhongwenWendang/js/libs/localforage.min.js
HginitZhongwenWendang/js/libs/screenfull.js
HginitZhongwenWendang/js/libs/screenfull.min.js
HginitZhongwenWendang/js/libs/zip.min.js
HginitZhongwenWendang/js/plugins/__init__.py
hginit_zhongwen_wendang-2024.3.1.0.dist-info/METADATA
hginit_zhongwen_wendang-2024.3.1.0.dist-info/WHEEL
hginit_zhongwen_wendang-2024.3.1.0.dist-info/entry_points.txt
hginit_zhongwen_wendang-2024.3.1.0.dist-info/top_level.txt
hginit_zhongwen_wendang-2024.3.1.0.dist-info/RECORD
